daft_launcher/__init__.py
daft_launcher/cli.py
daft_launcher/commands.py
daft_launcher/data_definitions.py
daft_launcher/helpers.py
daft_launcher/assets/aws.toml
daft_launcher/assets/sql.py
daft_launcher-0.4.0.dist-info/LICENSE
daft_launcher-0.4.0.dist-info/METADATA
daft_launcher-0.4.0.dist-info/WHEEL
daft_launcher-0.4.0.dist-info/entry_points.txt
daft_launcher-0.4.0.dist-info/top_level.txt
daft_launcher-0.4.0.dist-info/RECORD
