Metadata-Version: 2.1
Name: daft_launcher
Version: 0.4.0
Summary: A simple launcher for spinning up and managing Ray clusters for Daft.
License: Apache License
Requires-Python: >=3.9
License-File: LICENSE
Requires-Dist: boto3>=1.35.17
Requires-Dist: click>=8.1.7
Requires-Dist: ray[default]==2.37.0
Requires-Dist: tomli; python_version < "3.11"
